{"cameraMode":{"drawMode":0,"name":"Shaded","section":"Shading Mode"},"sceneLighting":false,"audioPlay":false,"sceneViewState":{"m_AlwaysRefresh":false,"showFog":true,"showSkybox":false,"showFlares":true,"showImageEffects":true,"showParticleSystems":true,"showVisualEffectGraphs":true,"m_FxEnabled":true},"in2DMode":false,"pivot":{"x":0.012270212173461914,"y":1.4454964399337769,"z":0.22782909870147706},"rotation":{"x":0.15045835077762605,"y":0.8471008539199829,"z":-0.323506236076355,"w":0.3939407765865326},"size":4.812733173370361,"orthographic":false}